square_logger/__init__.py
square_logger/main.py
square_logger-3.0.2.dist-info/WHEEL
square_logger-3.0.2.dist-info/METADATA
square_logger-3.0.2.dist-info/RECORD
