Metadata-Version: 2.3
Name: square-logger
Version: 3.0.2
Summary: python logger for my personal use.
Keywords: logger,utilities
Author: Parth Mukesh Mangtani, Amish Palkar
Author-email: Parth Mukesh Mangtani <thepmsquare@gmail.com>, Amish Palkar <amishpalkar302001@gmail.com>
License: GPLv3
Classifier: Development Status :: 3 - Alpha
Classifier: Intended Audience :: Developers
Classifier: License :: OSI Approved :: GNU General Public License v3 (GPLv3)
Classifier: Programming Language :: Python :: 3.12
Classifier: Topic :: Utilities
Classifier: Topic :: System :: Logging
Classifier: Topic :: Software Development :: Libraries :: Python Modules
Requires-Dist: pydantic>=2.5.3
Requires-Dist: pytest>=8.0.0 ; extra == 'test'
Requires-Dist: pytest-asyncio>=1.2.0 ; extra == 'test'
Requires-Python: >=3.12
Project-URL: homepage, https://github.com/thepmsquare/square_logger
Provides-Extra: test
